Metadata-Version: 2.1
Name: django-base-url
Version: 2020.7.1
Summary: {{ BASE_URL }} django template variable
Home-page: https://github.com/andrewp-as-is/django-base-url.py
License: Unlicense
Keywords: django base_url
Platform: UNKNOWN
Classifier: Framework :: Django
Classifier: License :: Public Domain
Classifier: Operating System :: OS Independent
Classifier: Programming Language :: Python :: 3
